vcs_versioning/__about__.py
vcs_versioning/__init__.py
vcs_versioning-0.0.1.dist-info/METADATA
vcs_versioning-0.0.1.dist-info/WHEEL
vcs_versioning-0.0.1.dist-info/licenses/LICENSE.txt
vcs_versioning-0.0.1.dist-info/RECORD
