Metadata-Version: 2.1
Name: vcs-versioning
Version: 0.0.1
Summary: the blessed package to manage your versions by vcs metadata
Project-URL: Documentation, https://github.com/unknown/vcs-versioning#readme
Project-URL: Issues, https://github.com/unknown/vcs-versioning/issues
Project-URL: Source, https://github.com/unknown/vcs-versioning
Author-email: Ronny Pfannschmidt <opensource@ronnypfannschmidt.de>
License-Expression: MIT
License-File: LICENSE.txt
Classifier: Development Status :: 1 - Planning
Classifier: Programming Language :: Python
Classifier: Programming Language :: Python :: 3.8
Classifier: Programming Language :: Python :: 3.9
Classifier: Programming Language :: Python :: 3.10
Classifier: Programming Language :: Python :: 3.11
Requires-Python: >=3.8
